wsection/W-section.csv
wsection/WSection.py
wsection/__init__.py
w_section-1.0.dist-info/METADATA
w_section-1.0.dist-info/WHEEL
w_section-1.0.dist-info/top_level.txt
w_section-1.0.dist-info/RECORD
