Metadata-Version: 2.1
Name: w-section
Version: 1.0
Summary: A python package to get properties of W-shaped steel section
Author: Wenchen Lie
Author-email: 666@e.gzhu.edu.cn
Requires-Dist: pandas
